tifftools/__init__.py
tifftools/__main__.py
tifftools/commands.py
tifftools/constants.py
tifftools/exceptions.py
tifftools/path_or_fobj.py
tifftools/tifftools.py
tifftools-1.7.0.dist-info/LICENSE
tifftools-1.7.0.dist-info/METADATA
tifftools-1.7.0.dist-info/WHEEL
tifftools-1.7.0.dist-info/entry_points.txt
tifftools-1.7.0.dist-info/top_level.txt
tifftools-1.7.0.dist-info/RECORD
