Metadata-Version: 2.1
Name: tifftools
Version: 1.7.0
Summary: Pure python tiff tools to handle all tags and IFDs.
Author-email: "Kitware, Inc." <kitware@kitware.com>
License: Apache-2.0
Project-URL: Repository, https://github.com/DigitalSlideArchive/tifftools
Keywords: tiff
Classifier: Development Status :: 5 - Production/Stable
Classifier: Natural Language :: English
Classifier: Programming Language :: Python :: 3
Classifier: Programming Language :: Python :: 3.8
Classifier: Programming Language :: Python :: 3.9
Classifier: Programming Language :: Python :: 3.10
Classifier: Programming Language :: Python :: 3.11
Classifier: Programming Language :: Python :: 3.12
Classifier: Programming Language :: Python :: 3.13
Classifier: Programming Language :: Python :: 3.14
Classifier: Topic :: Utilities
Requires-Python: >=3.8
License-File: LICENSE
Provides-Extra: geo
Requires-Dist: pyproj ; extra == 'geo'
